glhmm/auxiliary.py
glhmm/glhmm.py
glhmm/graphics.py
glhmm/io.py
glhmm/palm_functions.py
glhmm/prediction.py
glhmm/preproc.py
glhmm/spectral.py
glhmm/statistics.py
glhmm/utils.py
glhmm-1.1.1.dist-info/licenses/LICENSE
glhmm-1.1.1.dist-info/METADATA
glhmm-1.1.1.dist-info/WHEEL
glhmm-1.1.1.dist-info/top_level.txt
glhmm-1.1.1.dist-info/RECORD
