Metadata-Version: 2.4
Name: glhmm
Version: 1.1.1
Summary: Gaussian Linear Hidden Markov Model
Home-page: https://github.com/vidaurre/glhmm
Author: Diego Vidaurre
Author-email: Diego Vidaurre <dvidaurre@cfin.au.dk>
Classifier: Intended Audience :: Science/Research
Classifier: Programming Language :: Python :: 3
License-File: LICENSE
Requires-Dist: scipy
Requires-Dist: numpy
Requires-Dist: scikit-learn
Requires-Dist: matplotlib
Requires-Dist: numba
Requires-Dist: seaborn
Requires-Dist: pandas
Requires-Dist: igraph
Requires-Dist: tqdm
Requires-Dist: scikit-image
Requires-Dist: statsmodels
Requires-Dist: h5py
Requires-Dist: nibabel
Requires-Dist: requests
Requires-Dist: nilearn
Provides-Extra: doc
Requires-Dist: sphinx>=5.0; extra == "doc"
Requires-Dist: myst_parser; extra == "doc"
Requires-Dist: furo; extra == "doc"
Requires-Dist: nbsphinx; extra == "doc"
Dynamic: author
Dynamic: classifier
Dynamic: home-page
Dynamic: license-file
Dynamic: requires-dist
Dynamic: summary
